dash_cytoscape_elements/__init__.py
dash_cytoscape_elements/element.py
dash_cytoscape_elements/elements.py
dash_cytoscape_elements-0.0.4.dist-info/LICENSE
dash_cytoscape_elements-0.0.4.dist-info/WHEEL
dash_cytoscape_elements-0.0.4.dist-info/METADATA
dash_cytoscape_elements-0.0.4.dist-info/RECORD
