Metadata-Version: 2.1
Name: dash-cytoscape-elements
Version: 0.0.4
Summary: Python object for dash-cytoscape elements
Home-page: https://github.com/minefuto/dash-cytoscape-elements
License: MIT
Author: minefuto
Author-email: minefuto@gmail.com
Requires-Python: >=3.7,<4.0
Classifier: License :: OSI Approved :: MIT License
Classifier: Programming Language :: Python :: 3
Classifier: Programming Language :: Python :: 3.10
Classifier: Programming Language :: Python :: 3.7
Classifier: Programming Language :: Python :: 3.8
Classifier: Programming Language :: Python :: 3.9
Requires-Dist: pydantic (>=1.10.4,<2.0.0)
Project-URL: Repository, https://github.com/minefuto/dash-cytoscape-elements
